garagedoor_service/__init__.py
garagedoor_service/door_controller.py
garagedoor_service/main.py
garagedoor_service/gpio/GPIOAdapter.py
garagedoor_service/gpio/GPIOMockAdapter.py
garagedoor_service/gpio/GPIOPiAdapter.py
garagedoor_service/gpio/__init__.py
garagedoor_service/tools/api_key.py
garagedoor_service/tools/config.py
garagedoor_service-0.1.0.dist-info/LICENSE
garagedoor_service-0.1.0.dist-info/METADATA
garagedoor_service-0.1.0.dist-info/WHEEL
garagedoor_service-0.1.0.dist-info/entry_points.txt
garagedoor_service-0.1.0.dist-info/top_level.txt
garagedoor_service-0.1.0.dist-info/RECORD
