Metadata-Version: 2.1
Name: garagedoor_service
Version: 0.1.0
Summary: Garagedoor Service to drive a Chamberlain-style garage door opener using a Raspberry Pi
Author-email: Dusty Lefevre <dusty.lefevre@gmail.com>
License: MIT License
Requires-Python: ==3.12.*
License-File: LICENSE
Requires-Dist: fastapi>=0.112.2
Requires-Dist: rpi-gpio>=0.7.1
Requires-Dist: bcrypt>=4.2.0
